[
    {
        "title": "Estimation and mapping of soil texture content based on unmanned ... - Nature.com",
        "description": "Estimation and mapping of soil texture content based on unmanned ...  Nature.com",
        "published date": "Tue, 29 Aug 2023 07:00:00 GMT",
        "url": "https://consent.google.com/m?continue=https://news.google.com/rss/articles/CBMiMmh0dHBzOi8vd3d3Lm5hdHVyZS5jb20vYXJ0aWNsZXMvczQxNTk4LTAyMy00MDM4NC0y0gEA?oc%3D5&gl=IT&m=0&pc=n&cm=2&hl=en-US&src=1"
    },
    {
        "title": "Used Honda HR-V for Sale in Pakistan 2023 - Dispatch news Desk",
        "description": "Used Honda HR-V for Sale in Pakistan 2023  Dispatch news Desk",
        "published date": "Tue, 29 Aug 2023 07:00:00 GMT",
        "url": "https://consent.google.com/m?continue=https://news.google.com/rss/articles/CBMiQ2h0dHBzOi8vZG5kLmNvbS5way91c2VkLWhvbmRhLWhyLXYtZm9yLXNhbGUtaW4tcGFraXN0YW4tMjAyMy8zMDAwNzPSAQA?oc%3D5&gl=IT&m=0&pc=n&cm=2&hl=en-US&src=1"
    }
]