[
    {
        "title": "Japan shares lower at close of trade; Nikkei 225 down 1.83% - Investing.com South Africa",
        "description": "Japan shares lower at close of trade; Nikkei 225 down 1.83%  Investing.com South Africa",
        "published date": "Tue, 03 Oct 2023 07:52:53 GMT",
        "url": "https://consent.google.com/m?continue=https://news.google.com/rss/articles/CBMiXmh0dHBzOi8vemEuaW52ZXN0aW5nLmNvbS9uZXdzL2phcGFuLXNoYXJlcy1sb3dlci1hdC1jbG9zZS1vZi10cmFkZS1uaWtrZWktMjI1LWRvd24tMTgzLTI4ODM0MzXSAQA?oc%3D5&gl=IT&m=0&pc=n&cm=2&hl=en-US&src=1"
    },
    {
        "title": "Sony's PlayStation Portal Has Already Sold Out In Japan – Pokde.Net - Pokde.Net",
        "description": "Sony's PlayStation Portal Has Already Sold Out In Japan – Pokde.Net  Pokde.Net",
        "published date": "Wed, 04 Oct 2023 07:00:00 GMT",
        "url": "https://consent.google.com/m?continue=https://news.google.com/rss/articles/CBMiRmh0dHBzOi8vcG9rZGUubmV0L2dhZGdldC9oYW5kaGVsZC9wbGF5c3RhdGlvbi1wb3J0YWwtc29sZC1vdXQtaW4tamFwYW7SAQA?oc%3D5&gl=IT&m=0&pc=n&cm=2&hl=en-US&src=1"
    }
]