[
    {
        "title": "7 Up-and-Coming AI Stocks to Put on Your Must-Buy List - InvestorPlace",
        "description": "7 Up-and-Coming AI Stocks to Put on Your Must-Buy List  InvestorPlace",
        "published date": "Thu, 31 Aug 2023 07:00:00 GMT",
        "url": "https://consent.google.com/m?continue=https://news.google.com/rss/articles/CBMiWWh0dHBzOi8vaW52ZXN0b3JwbGFjZS5jb20vMjAyMy8wOC83LXVwLWFuZC1jb21pbmctYWktc3RvY2tzLXRvLXB1dC1vbi15b3VyLW11c3QtYnV5LWxpc3Qv0gEA?oc%3D5&gl=IT&m=0&pc=n&cm=2&hl=en-US&src=1"
    },
    {
        "title": "7 Growth Stocks the Big Money Is Buying Now - InvestorPlace",
        "description": "7 Growth Stocks the Big Money Is Buying Now  InvestorPlace",
        "published date": "Thu, 31 Aug 2023 07:00:00 GMT",
        "url": "https://consent.google.com/m?continue=https://news.google.com/rss/articles/CBMiTmh0dHBzOi8vaW52ZXN0b3JwbGFjZS5jb20vMjAyMy8wOC83LWdyb3d0aC1zdG9ja3MtdGhlLWJpZy1tb25leS1pcy1idXlpbmctbm93L9IBAA?oc%3D5&gl=IT&m=0&pc=n&cm=2&hl=en-US&src=1"
    }
]