[
    {
        "title": "Latest On Alek Manoah - MLB Trade Rumors",
        "description": "Latest On Alek Manoah  MLB Trade Rumors",
        "published date": "Wed, 13 Sep 2023 07:00:00 GMT",
        "url": "https://consent.google.com/m?continue=https://news.google.com/rss/articles/CBMiQWh0dHBzOi8vd3d3Lm1sYnRyYWRlcnVtb3JzLmNvbS8yMDIzLzA5L2xhdGVzdC1vbi1hbGVrLW1hbm9haC5odG1s0gEA?oc%3D5&gl=IT&m=0&pc=n&cm=2&hl=en-US&src=1"
    },
    {
        "title": "K-popartieste IU komt met concertfilm 'IU CONCERT: The Golden ... - newsmonkey",
        "description": "K-popartieste IU komt met concertfilm 'IU CONCERT: The Golden ...  newsmonkey",
        "published date": "Wed, 13 Sep 2023 07:00:00 GMT",
        "url": "https://consent.google.com/m?continue=https://news.google.com/rss/articles/CBMiWmh0dHBzOi8vbmV3c21vbmtleS5iZS9rLXBvcGFydGllc3RlLWl1LWNvbmNlcnRmaWxtLWl1LWNvbmNlcnQtdGhlLWdvbGRlbi1ob3VyLWNpbmVtYXphbGVuL9IBAA?oc%3D5&gl=IT&m=0&pc=n&cm=2&hl=en-US&src=1"
    }
]