[
    {
        "title": "Biden Awards $7 Billion For 7 Hydrogen Hubs In Climate Fight Plan - Slashdot",
        "description": "Biden Awards $7 Billion For 7 Hydrogen Hubs In Climate Fight Plan  Slashdot",
        "published date": "Fri, 13 Oct 2023 07:00:00 GMT",
        "url": "https://consent.google.com/m?continue=https://news.google.com/rss/articles/CBMicGh0dHBzOi8veXJvLnNsYXNoZG90Lm9yZy9zdG9yeS8yMy8xMC8xMy8yMjIzMjE0L2JpZGVuLWF3YXJkcy03LWJpbGxpb24tZm9yLTctaHlkcm9nZW4taHVicy1pbi1jbGltYXRlLWZpZ2h0LXBsYW7SAQA?oc%3D5&gl=IT&m=0&pc=n&cm=2&hl=en-US&src=1"
    },
    {
        "title": "Genesis IT AB flyttas till observationslistan / Genesis IT AB will be ... - swedbank-aktiellt.se",
        "description": "Genesis IT AB flyttas till observationslistan / Genesis IT AB will be ...  swedbank-aktiellt.se",
        "published date": "Fri, 13 Oct 2023 07:05:52 GMT",
        "url": "https://consent.google.com/m?continue=https://news.google.com/rss/articles/CBMiMmh0dHBzOi8vd3d3LnN3ZWRiYW5rLWFrdGllbGx0LnNlL3RlbGVncmFtL2N2MFRsejZB0gEA?oc%3D5&gl=IT&m=0&pc=n&cm=2&hl=en-US&src=1"
    }
]